{
   "Character" : [
      {
         "ID" : 1,
         "Name" : "梅普露(本条枫)",
         "CV" : "本渡 楓",
         "Picture" : "1.png",
         "intro" : "本名是本条枫。全部点满防御，成为无论什么样的攻击都能防御的大盾角色，但是本人却没有意识到自己的防御力异常，任何售后都能享受快乐的性格，有着暴走的好奇心。",
         "code" : "Maple"
      },
      {
         "ID" : 2,
         "Name" : "莎莉(白峰理沙)",
         "CV" : "野口瑠璃子",
         "Picture" : "2.png",
         "intro" : "本名是白峰理沙。是枫的挚友，邀请枫来玩VRMMO『NewWorld Online』的人。游戏经验丰富，集中力超群，能够躲开所有攻击技能。是一个为朋友着想的人。 ",
         "code" : "Sally"
      },
      {
         "ID" : 3,
         "Name" : "霞",
         "CV" : "早見沙織",
         "Picture" : "3.png",
         "intro" : "イベントで上位に入賞したことのある刀使い。生真面目な常識人で、冷静に戦況を見極め的確な判断で行動する。攻撃力と敏捷性が高く、敵に安定したダメージを与えられる。",
         "code" : "Kasumi"
      },
      {
         "ID" : 4,
         "Name" : "奏",
         "CV" : "新井里美",
         "Picture" : "4.png",
         "intro" : "色白で中性的な顔立ちをした記憶力抜群の天才少年。特殊なスキルが使えるというルービックキューブ型の杖を使用する。笑顔を絶やさないが、本心が見えず掴みどころがない。",
         "code" : "Kanade"
      },
      {
         "ID" : 5,
         "Name" : "麻衣",
         "CV" : "加隈亜衣",
         "Picture" : "5.png",
         "intro" : "攻撃力に極振りした初心者プレイヤー。ユイの双子の姉。慎重すぎる性格で、 やや優柔不断かつ心配性なところもあるが、みんなに迷惑をかけないよう精一杯努力している。",
         "code" : "May"
      },
      {
         "ID" : 6,
         "Name" : "结衣",
         "CV" : "諏訪ななか",
         "Picture" : "6.png",
         "intro" : "攻撃力に極振りした初心者プレイヤー。マイの双子の妹。マイに比べ、前向きで積極的な性格。心配性のマイを気遣うことが多い。双子揃って楓の木のメンバーに鍛えられる。",
         "code" : "Yui"
      },
      {
         "ID" : 7,
         "Name" : "克罗姆",
         "CV" : "杉山紀彰",
         "Picture" : "7.png",
         "intro" : "『NewWorld Online』のトッププレイヤーで、メイプルと同じ大盾使い。前衛で大盾によって攻撃を弾き、パーティーを守る堅実な戦い方を徹底している。面倒見のよい兄貴肌。",
         "code" : "Kuromu"
      },
      {
         "ID" : 8,
         "Name" : "伊兹",
         "CV" : "佐藤聡美",
         "Picture" : "8.png",
         "intro" : "生産に特化したプレイヤー。武器と防具の鍛冶が専門だが、アクセサリーやアイテムの製作、製造など生産に関することはなんでもできる。モノづくりへのこだわりが強い。",
         "code" : "Iz"
      }
   ]
}
